{
  "status": "PASS_WITH_WARNINGS",
  "raw_row_count": 4977,
  "output_row_count": 4977,
  "duplicate_key_count": 0,
  "unique_key": [
    "record_date",
    "security_type",
    "security_description"
  ],
  "unique_key_count": 4977,
  "null_counts": {
    "record_date": 0,
    "security_type": 0,
    "security_description": 0,
    "average_interest_rate_percent": 28,
    "source_line_number": 0,
    "fiscal_year": 0,
    "fiscal_quarter": 0,
    "calendar_year": 0,
    "calendar_quarter": 0,
    "calendar_month": 0,
    "calendar_day": 0,
    "source_url": 0
  },
  "primary_key_null_count": 0,
  "min_record_date": "2001-01-31",
  "max_record_date": "2026-06-30",
  "validation_issues": [
    "row 703: source interest rate is null",
    "row 704: source interest rate is null",
    "row 720: source interest rate is null",
    "row 721: source interest rate is null",
    "row 735: source interest rate is null",
    "row 736: source interest rate is null",
    "row 752: source interest rate is null",
    "row 753: source interest rate is null",
    "row 769: source interest rate is null",
    "row 770: source interest rate is null",
    "row 786: source interest rate is null",
    "row 787: source interest rate is null",
    "row 803: source interest rate is null",
    "row 804: source interest rate is null",
    "row 820: source interest rate is null",
    "row 821: source interest rate is null",
    "row 837: source interest rate is null",
    "row 838: source interest rate is null",
    "row 854: source interest rate is null",
    "row 855: source interest rate is null",
    "row 871: source interest rate is null",
    "row 872: source interest rate is null",
    "row 888: source interest rate is null",
    "row 889: source interest rate is null",
    "row 905: source interest rate is null",
    "row 906: source interest rate is null",
    "row 922: source interest rate is null",
    "row 923: source interest rate is null"
  ]
}
